{
    "ググプラム": "100021",
    "ヴァルベリー": "100022",
    "セシリアの花": "100023",
    "風車アスター": "100024",
    "慕風のマッシュルーム": "100025",
    "絶雲の唐辛子": "100027",
    "夜泊石": "100028",
    "霓裳花": "100029",
    "琉璃百合": "100030",
    "清心": "100031",
    "星螺": "100033",
    "琉璃袋": "100034",
    "イグサ": "100055",
    "ドドリアン": "100056",
    "蒲公英の種": "100057",
    "石珀": "100058",
    "オニカブトムシ": "101201",
    "緋櫻毬": "101202",
    "晶化骨髄": "101203",
    "血石華": "101204",
    "鳴草": "101205",
    "ウミレイシ": "101206",
    "珊瑚真珠": "101207",
    "天雲草の実": "101208",
    "ユウトウタケ": "101209",
    "ルッカデヴァータダケ": "101213",
    "パティサラ": "101214",
    "サウマラタ蓮": "101215",
    "カルパラタ蓮": "101217",
    "赤念の実": "101220",
    "聖金虫": "101225",
    "輝くダイヤ・砕屑": "104101",
    "輝くダイヤ・欠片": "104102",
    "輝くダイヤ・塊": "104103",
    "輝くダイヤ": "104104",
    "炎願のアゲート・砕屑": "104111",
    "炎願のアゲート・欠片": "104112",
    "炎願のアゲート・塊": "104113",
    "炎願のアゲート": "104114",
    "澄明なラピスラズリ・砕屑": "104121",
    "澄明なラピスラズリ・欠片": "104122",
    "澄明なラピスラズリ・塊": "104123",
    "澄明なラピスラズリ": "104124",
    "成長のエメラルド・砕屑": "104131",
    "成長のエメラルド・欠片": "104132",
    "成長のエメラルド・塊": "104133",
    "成長のエメラルド": "104134",
    "最勝のアメシスト・砕屑": "104141",
    "最勝のアメシスト・欠片": "104142",
    "最勝のアメシスト・塊": "104143",
    "最勝のアメシスト": "104144",
    "自由のターコイズ・砕屑": "104151",
    "自由のターコイズ・欠片": "104152",
    "自由のターコイズ・塊": "104153",
    "自由のターコイズ": "104154",
    "哀切なアイスクリスタル・砕屑": "104161",
    "哀切なアイスクリスタル・欠片": "104162",
    "哀切なアイスクリスタル・塊": "104163",
    "哀切なアイスクリスタル": "104164",
    "堅牢なトパーズ・砕屑": "104171",
    "堅牢なトパーズ・欠片": "104172",
    "堅牢なトパーズ・塊": "104173",
    "堅牢なトパーズ": "104174",
    "「自由」の教え": "104301",
    "「自由」の導き": "104302",
    "「自由」の哲学": "104303",
    "自由(月・木)": "104303",
    "「抗争」の教え": "104304",
    "「抗争」の導き": "104305",
    "「抗争」の哲学": "104306",
    "抗争(火・金)": "104306",
    "「詩文」の教え": "104307",
    "「詩文」の導き": "104308",
    "「詩文」の哲学": "104309",
    "詩文(水・土)": "104309",
    "「繁栄」の教え": "104310",
    "「繁栄」の導き": "104311",
    "「繁栄」の哲学": "104312",
    "繁栄(月・木)": "104312",
    "「勤労」の教え": "104313",
    "「勤労」の導き": "104314",
    "「勤労」の哲学": "104315",
    "勤労(火・金)": "104315",
    "「黄金」の教え": "104316",
    "「黄金」の導き": "104317",
    "「黄金」の哲学": "104318",
    "黄金(水・土)": "104318",
    "知恵の冠": "104319",
    "「浮世」の教え": "104320",
    "「浮世」の導き": "104321",
    "「浮世」の哲学": "104322",
    "浮世(月・木)": "104322",
    "「風雅」の教え": "104323",
    "「風雅」の導き": "104324",
    "「風雅」の哲学": "104325",
    "風雅(火・金)": "104325",
    "「天光」の教え": "104326",
    "「天光」の導き": "104327",
    "「天光」の哲学": "104328",
    "天光(水・土)": "104328",
    "「忠言」の教え": "104329",
    "「忠言」の導き": "104330",
    "「忠言」の哲学": "104331",
    "忠言(月・木)": "104331",
    "「創意」の教え": "104332",
    "「創意」の導き": "104333",
    "「創意」の哲学": "104334",
    "創意(火・金)": "104334",
    "「篤行」の教え": "104335",
    "「篤行」の導き": "104336",
    "「篤行」の哲学": "104337",
    "篤行(水・土)": "104337",
    "スライムの液体": "112002",
    "スライムの分泌物": "112003",
    "スライムのピュレ": "112004",
    "スライム": "112004",
    "破損した仮面": "112005",
    "汚れた仮面": "112006",
    "不吉な仮面": "112007",
    "仮面": "112007",
    "占いの絵巻": "112008",
    "封魔の絵巻": "112009",
    "禁呪の絵巻": "112010",
    "絵巻": "112010",
    "牢固な矢先": "112011",
    "鋭利な矢先": "112012",
    "歴戦の矢先": "112013",
    "矢先": "112013",
    "重い角笛": "112014",
    "黒銅の角笛": "112015",
    "黒晶の角笛": "112016",
    "暗晦の彫刻": "112017",
    "黒夜の彫刻": "112018",
    "幽邃なる彫刻": "112019",
    "地脈の旧枝": "112020",
    "地脈の枯れ葉": "112021",
    "地脈の新芽": "112022",
    "混沌の装置": "112023",
    "混沌の回路": "112024",
    "混沌の炉心": "112025",
    "霧虚ろの花粉": "112026",
    "霧虚ろの草嚢": "112027",
    "霧虚ろの灯芯": "112028",
    "猟兵の刀": "112029",
    "エージェントの刀": "112030",
    "検査官の刀": "112031",
    "新兵の記章": "112032",
    "士官の記章": "112033",
    "尉官の記章": "112034",
    "記章": "112034",
    "宝探しの鴉マーク": "112035",
    "シルバーの鴉マーク": "112036",
    "ゴールドの鴉マーク": "112037",
    "鴉マーク": "112037",
    "トリックフラワーの蜜": "112038",
    "微光花の蜜": "112039",
    "原素花の蜜": "112040",
    "蜜": "112040",
    "脆い骨片": "112041",
    "丈夫な骨片": "112042",
    "石化した骨片": "112043",
    "骨片": "112043",
    "古びた鍔": "112044",
    "影打の鍔": "112045",
    "名刀の鍔": "112046",
    "鍔": "112046",
    "混沌の機関": "112047",
    "混沌の中枢": "112048",
    "混沌の真眼": "112049",
    "暗色プリズム": "112050",
    "水晶プリズム": "112051",
    "偏光プリズム": "112052",
    "フライムの乾核": "112053",
    "フライムの幽核": "112054",
    "フライムの晶化核": "112055",
    "フライム": "112055",
    "隠獣の指爪": "112056",
    "隠獣の利爪": "112057",
    "隠獣の鬼爪": "112058",
    "キノコンの胞子": "112059",
    "キノコンの蛍胞子": "112060",
    "キノコンの晶胞子": "112061",
    "胞子(キノコン)": "112061",
    "キノコンの衰菌核": "112062",
    "キノコンの眠菌核": "112063",
    "キノコンの壮菌核": "112064",
    "色褪せた赤い絹": "112065",
    "縁飾の赤い絹": "112066",
    "金織の赤い絹": "112067",
    "絹(旅団)": "112067",
    "混沌ストレージ": "112068",
    "混沌モジュール": "112069",
    "混沌ボルト": "112070",
    "壊れたプリズム": "112071",
    "濁ったプリズム": "112072",
    "輝くプリズム": "112073",
    "暴風の種": "113001",
    "雷光のプリズム": "113002",
    "東風の羽根": "113003",
    "東風の爪": "113004",
    "東風の吐息": "113005",
    "北風のしっぽ": "113006",
    "北風のリング": "113007",
    "北風の魂箱": "113008",
    "玄岩の塔": "113009",
    "極寒のコア": "113010",
    "常燃の火種": "113011",
    "浄水の心": "113012",
    "呑天の鯨・只角": "113013",
    "魔王の刃・残片": "113014",
    "武煉の魂・孤影": "113015",
    "未熟の玉石": "113016",
    "龍王の冠": "113017",
    "血玉の枝": "113018",
    "鍍金の鱗": "113019",
    "凝結の華": "113020",
    "魔偶の芯": "113022",
    "恒常からくりの芯": "113023",
    "陰燃の珠": "113024",
    "溶滅の刻": "113025",
    "獄炎の蝶": "113026",
    "灰燼の心": "113027",
    "排他の露": "113028",
    "雷霆の念珠": "113029",
    "獣域王器": "113030",
    "ドラゴエアのニセヒレ": "113031",
    "凶将の手眼": "113032",
    "禍神の禊涙": "113033",
    "万劫の真意": "113034",
    "符文の歯車": "113035",
    "茸王の鉤状のくちばし": "113036",
    "隠雷の実": "113037",
    "永続コア": "113038",
    "導光四面体": "113039",
    "滅諍の蔓": "113040",
    "傀儡の糸": "113041",
    "無心の淵鏡": "113042",
    "空行の虚鈴": "113043"
}